devlama/DependencyManager.py
devlama/OllamaRunner.py
devlama/__init__.py
devlama/api.py
devlama/cli.py
devlama/dependency_utils.py
devlama/devlama.py
devlama/ecosystem/__init__.py
devlama/ecosystem/cli.py
devlama/ecosystem/config.py
devlama/ecosystem/ecosystem_manager.py
devlama/ecosystem/log_manager.py
devlama/ecosystem/logging_config.py
devlama/ecosystem/port_utils.py
devlama/ecosystem/service_utils.py
devlama/ecosystem.py
devlama/examples/api_request.py
devlama/examples/database.py
devlama/examples/default.py
devlama/examples/file_io.py
devlama/examples/web_server.py
devlama/logging_config.py
devlama/py.typed
devlama/pybox_wrapper.py
devlama/pyllm_wrapper.py
devlama/templates.py
devlama-0.1.16.dist-info/LICENSE
devlama-0.1.16.dist-info/METADATA
devlama-0.1.16.dist-info/WHEEL
devlama-0.1.16.dist-info/entry_points.txt
devlama-0.1.16.dist-info/RECORD
