Metadata-Version: 2.3
Name: devlama
Version: 0.1.16
Summary: Python code generation and execution using Ollama language models
License: Apache-2.0
Author: John Doe
Author-email: john.doe@example.com
Requires-Python: >=3.8
Classifier: License :: OSI Approved :: Apache Software License
Classifier: Programming Language :: Python :: 3
Classifier: Programming Language :: Python :: 3.8
Classifier: Programming Language :: Python :: 3.9
Classifier: Programming Language :: Python :: 3.10
Classifier: Programming Language :: Python :: 3.11
Classifier: Programming Language :: Python :: 3.12
Classifier: Programming Language :: Python :: 3.13
Requires-Dist: fastapi (>=0.103.1,<0.104.0)
Requires-Dist: python-dotenv (>=1.0.0)
Requires-Dist: requests (>=2.31.0)
Requires-Dist: uvicorn (>=0.23.2,<0.24.0)
